esa_climate_toolbox/__init__.py
esa_climate_toolbox/constants.py
esa_climate_toolbox/plugin.py
esa_climate_toolbox/version.py
esa_climate_toolbox/conf/__init__.py
esa_climate_toolbox/conf/conf.py
esa_climate_toolbox/conf/defaults.py
esa_climate_toolbox/conf/template.py
esa_climate_toolbox/core/__init__.py
esa_climate_toolbox/core/common.py
esa_climate_toolbox/core/ds.py
esa_climate_toolbox/core/op.py
esa_climate_toolbox/core/opchain.py
esa_climate_toolbox/core/opimpl.py
esa_climate_toolbox/core/plugin.py
esa_climate_toolbox/core/types.py
esa_climate_toolbox/ds/__init__.py
esa_climate_toolbox/ds/geodataframe.py
esa_climate_toolbox/ds/data/stores.yml
esa_climate_toolbox/functions/__init__.py
esa_climate_toolbox/functions/outputarray.py
esa_climate_toolbox/functions/regions.py
esa_climate_toolbox/functions/country_data/README.md
esa_climate_toolbox/functions/country_data/__init__.py
esa_climate_toolbox/functions/country_data/countries.geojson
esa_climate_toolbox/ops/__init__.py
esa_climate_toolbox/ops/aggregate.py
esa_climate_toolbox/ops/animate.py
esa_climate_toolbox/ops/anomaly.py
esa_climate_toolbox/ops/arithmetics.py
esa_climate_toolbox/ops/coregistration.py
esa_climate_toolbox/ops/correlation.py
esa_climate_toolbox/ops/data_frame.py
esa_climate_toolbox/ops/gapfilling.py
esa_climate_toolbox/ops/normalize.py
esa_climate_toolbox/ops/outliers.py
esa_climate_toolbox/ops/plot.py
esa_climate_toolbox/ops/plot_helpers.py
esa_climate_toolbox/ops/resampling.py
esa_climate_toolbox/ops/select.py
esa_climate_toolbox/ops/subset.py
esa_climate_toolbox/ops/timeseries.py
esa_climate_toolbox/ops/utility.py
esa_climate_toolbox/util/__init__.py
esa_climate_toolbox/util/misc.py
esa_climate_toolbox/util/monitor.py
esa_climate_toolbox/util/opmetainf.py
esa_climate_toolbox/util/process.py
esa_climate_toolbox/util/reporting.py
esa_climate_toolbox/util/safe.py
esa_climate_toolbox/util/sround.py
esa_climate_toolbox/util/time.py
esa_climate_toolbox/util/tmpfile.py
esa_climate_toolbox-1.5.1.dist-info/licenses/LICENSE
esa_climate_toolbox-1.5.1.dist-info/METADATA
esa_climate_toolbox-1.5.1.dist-info/WHEEL
esa_climate_toolbox-1.5.1.dist-info/entry_points.txt
esa_climate_toolbox-1.5.1.dist-info/top_level.txt
esa_climate_toolbox-1.5.1.dist-info/RECORD
