Metadata-Version: 2.4
Name: esa_climate_toolbox
Version: 1.5.1
Summary: The ESA CCI Toolbox is designed to provide access to CCI data
Author: ESA CCI Toolbox Development Team
License: MIT License
Project-URL: Homepage, https://github.com/esa-cci/esa-climate-toolbox
Project-URL: Bug Tracker, https://github.com/esa-cci/esa-climate-toolbox/issues
Project-URL: Changelog, https://github.com/esa-cci/esa-climate-toolbox/CHANGES.md
Project-URL: Documentation, https://esa-climate-toolbox.readthedocs.io
Project-URL: Download, https://pypi.org/project/esa-climate-toolbox/#files
Project-URL: Release notes, https://github.com/esa-cci/esa-climate-toolbox/releases
Keywords: data science,cci,climate data
Classifier: Programming Language :: Python
Classifier: Programming Language :: Python :: 3
Classifier: Programming Language :: Python :: 3.10
Classifier: Programming Language :: Python :: 3.11
Classifier: License :: OSI Approved :: MIT License
Classifier: Operating System :: OS Independent
Requires-Python: >=3.10
License-File: LICENSE
Requires-Dist: cartopy
Requires-Dist: cftime
Requires-Dist: dask
Requires-Dist: geopandas
Requires-Dist: lxml>=4.5
Requires-Dist: matplotlib
Requires-Dist: nest-asyncio>=1.3
Requires-Dist: numcodecs
Requires-Dist: numba>0.35
Requires-Dist: numpy>=2
Requires-Dist: pandas
Requires-Dist: pyproj
Requires-Dist: python-dateutil
Requires-Dist: shapely
Requires-Dist: simplekml
Requires-Dist: six
Requires-Dist: xarray
Requires-Dist: xcube-core>=1.4.0
Requires-Dist: xcube-cci>=0.11.1
Provides-Extra: dev
Requires-Dist: pytest; extra == "dev"
Requires-Dist: pytest-cov; extra == "dev"
Dynamic: license-file
